Workbook

Sheet 填写说明
B2: 绿色工厂数据采集表（GB/T 36132—2025 / 14项指标）
B3: v1.1.1 政策核对至 2026-10-23；表内为虚构演示数据，请整体覆盖后使用
B5: 事项 | C5: 说明
B6: 怎么填 | C6: 按 1→5 页顺序填写蓝字黄底的格子，第6页自动算分。下拉格从列表选，不要手打。
B7: 颜色 | C7: 蓝字黄底=需要填写；黑字=公式自动计算，请勿修改。
B8: 数据年份 | C8: 强度和比率类指标都用评价年（申报年份的上一自然年）全年数据；指标10用近三年投资和三年产值。
B9: 口径一致 | C9: 强度指标按产值还是产量，要和对标值口径一致；产值用统计报表的工业总产值（现价），不是营业收入。
B10: 对标值 | C10: 对标值决定得分。没有可靠来源就留空，第6页会显示“缺对标值”，宁可待定也不要估。
B11: 重点行业 | C11: 属于重点行业的，平台按行业评价要求打分，指标和对标值可能与本表不同，以平台为准。
B12: 交给智能体 | C12: 把填好的表发给“绿色工厂研判”技能，它会读取输入格，生成研判结论和 Word 报告。
B13: 数据安全 | C13: 本表在本机打开即可计算，不联网。发给任何在线服务前，请确认企业允许外传这些数据。
B15: 示例 | C15: 演示企业：齿轮及齿轮减、变速箱制造，江苏，非重点行业，目标省级，2025年数据。按演示对标值，第6页应显示确定分63.9、待定14、上限77.9、结论“有希望，待补齐”。
B16: 百分比 | C16: 指标3、7、8、10的对标值按百分数填，如12%填12；直接输入“12%”也会自动识别，不会算错。
B17: 说明 | C17: 本表按 GB/T 36132—2025 和公开政策的规则计算，结果是推算，不是第三方评价报告，也不是主管部门的评审结论。

Sheet 1基本信息
B2: 1 基本信息与门槛
B3: 蓝字黄底格填写；下拉格请从列表选择。表中现有内容是虚构的演示企业，请整体覆盖
B5: 项目 | C5: 填写 | D5: 说明
B6: 企业名称（申报主体，独立法人或视同法人的独立核算单位） | C6: 示例传动科技有限公司（演示数据）
B7: 所在省份 | C7: 江苏 | D7: 用于选取电力排放因子
B8: 所属行业（按 GB/T 4754） | C8: 齿轮及齿轮减、变速箱制造
B9: 行业代码 | C9: C3453 | D9: 如 C3453
B10: 是否属于C类制造业 | C10: 是 | D10: 非C类不能申报国家绿色工厂
B11: 是否属于重点行业 | C11: 否 | D11: 以管理平台显示的行业评价要求为准
B12: 本次目标层级 | C12: 省级 | D12: 京津沪渝选“市级”会按省级处理；计划单列市以本市通知为准
B13: 当前已获层级 | C13: 市级 | D13: 国家级须先列入本地区省级名单；京津沪渝的市级名单即省级
B14: 评价年 | C14: 2025 | D14: 申报年份的上一自然年
B15: 智能工厂等级 | C15: 先进级 | D15: 卓越级、领航级国家级优先推荐
B16: 已获荣誉（用顿号分隔） | C16: 专精特新 | D16: 如能效领跑者、专精特新、小巨人
B17: 强度指标口径 | C17: 产值 | D17: 产值或产量，须与对标值口径一致
B18: 产品计量单位 | C18: 台 | D18: 按产量口径时使用
B20: 近三年否决情形 | C20: 否/是/不确定 | D20: 说明
B21: 近三年未正常经营生产（注销、连续停产12个月以上、列入经营异常名录未移出等） | C21: 否 | D21: 任何一项为“是”即不能申报
B22: 近三年发生较大及以上安全（含网络、数据、生产安全）、质量、环境污染事故 | C22: 否 | D22: 任何一项为“是”即不能申报
B23: 近三年被动态调整出绿色制造名单 | C23: 否 | D23: 任何一项为“是”即不能申报
B24: 近三年从事《反垄断法》规定的垄断行为 | C24: 否 | D24: 任何一项为“是”即不能申报
B25: 近三年在国务院及有关部门督查中被发现存在严重问题 | C25: 否 | D25: 任何一项为“是”即不能申报
B26: 被列入工业节能监察整改名单且未按要求完成整改 | C26: 否 | D26: 任何一项为“是”即不能申报
B27: 近三年受到有关行政主管部门比较重大以上行政处罚 | C27: 否 | D27: 任何一项为“是”即不能申报
... B38: 分数线（留空则用缺省值） | C38: 分 | D38: 说明
B39: 市级分数线 | D39: 以当地通知为准
B40: 省级分数线 | D40: 留空：重点行业60、非重点75（安徽2026口径）
B41: 本地区已有国家绿色工厂平均分（如了解） | D41: 国家级无固定分数线，用于比较

Sheet 2能源与碳
B2: 2 能源与碳（评价年全年）
B3: 只填C列；E—H列自动计算。外购电量按电费结算单，光伏按发电计量表的自用电量
B4: 项目 | C4: 数量 | D4: 单位 | E4: 折标系数 | F4: 折标量 tce | G4: 排放因子 | H4: 排放量 tCO2 | I4: 说明
B5: 外购电网电量（含绿电交易电量） | C5: 18900000 | D5: kWh | E5: =参数!$E$4 -> 0.1229 | F5: =C5*E5/1000 -> 2322.81 | G5: =$C$33 -> 0.5827 | H5: =IF($C$25="市场法",MAX(C5-$C$29,0),C5)*G5/1000 -> 11013.03 | I5: 按电费结算单
B6: 自发自用光伏等可再生电量 | C6: 2600000 | D6: kWh | E6: =参数!$E$4 -> 0.1229 | F6: =C6*E6/1000 -> 319.54 | G6: 0 | H6: =C6*G6/1000 -> 0 | I6: 计入能耗，零排放
B7: 专线直供可再生电量 | D7: kWh | E7: =参数!$E$4 -> 0.1229 | F7: =C7*E7/1000 -> 0 | G7: 0 | H7: =C7*G7/1000 -> 0 | I7: 需交易结算凭证
B8: 其中：市场化交易绿电电量 | C8: 0 | D8: kWh | I8: 已含在第5行，不重复计入能耗
B9: 单独购买的绿证 | C9: 0 | D9: MWh | I9: 1张=1 MWh；绿电交易附带的绿证不要再填
B10: 天然气 | C10: 380000 | D10: m³ | E10: =IF($C$27="",参数!$E$5,$C$27) -> 1.2143 | F10: =C10*E10/1000 -> 461.434 | G10: =参数!$M$4 -> 0.0021650152 | H10: =C10*G10 -> 822.70578
B11: 柴油 | C11: 45 | D11: t | E11: =参数!$E$6 -> 1.4571 | F11: =C11*E11 -> 65.5695 | G11: =参数!$M$5 -> 3.0959096 | H11: =C11*G11 -> 139.31593 | I11: 厂内运输和设备用
B12: 汽油 | C12: 12 | D12: t | E12: =参数!$E$7 -> 1.4714 | F12: =C12*E12 -> 17.6568 | G12: =参数!$M$6 -> 2.925056 | H12: =C12*G12 -> 35.100672
B13: 液化石油气 | D13: t | E13: =参数!$E$8 -> 1.7143 | F13: =C13*E13 -> 0 | G13: =参数!$M$7 -> 3.1013298 | H13: =C13*G13 -> 0
B14: 燃料油 | D14: t | E14: =参数!$E$9 -> 1.4286 | F14: =C14*E14 -> 0 | G14: =参数!$M$8 -> 3.1704612 | H14: =C14*G14 -> 0
B15: 原煤 | D15: t | E15: =参数!$E$10 -> 0.7143 | F15: =C15*E15 -> 0 | G15: =参数!$M$9 -> 1.9002988 | H15: =C15*G15 -> 0
B16: 焦炭 | D16: t | E16: =参数!$E$11 -> 0.9714 | F16: =C16*E16 -> 0 | G16: =参数!$M$10 -> 2.8604188 | H16: =C16*G16 -> 0
B17: 外购热力（蒸汽按供汽方提供的热量折GJ） | D17: GJ | E17: =参数!$E$12 -> 34.12 | F17: =C17*E17/1000 -> 0 | G17: =参数!$M$11 -> 0.11 | H17: =C17*G17 -> 0
B18: 其他化石能源（已折标） | D18: tce | F18: =C18 -> 0 | I18: 其排放请填在第20行
B19: 其他可再生能源（非电，已折标） | D19: tce | F19: =C19 -> 0 | I19: 生物质、太阳能热利用等
B20: 过程排放及其他排放 | D20: tCO2 | H20: =C20 -> 0
B21: 用作原料的能源（扣除） | D21: tce | F21: =-C21 -> 0 | I21: 化工原料用气、用煤等
B22: 外供能源（扣除） | D22: tce | F22: =-C22 -> 0
B24: 口径设置 | C24: 填写 | D24: 说明
B25: 碳排放口径 | C25: 地区平均因子 | D25: 地区平均因子（缺省）或市场法；与平台要求一致，不要混用
B26: 电网排放因子覆盖值 kgCO2/kWh（留空自动取） | D26: 当地或平台另有规定时填
B27: 天然气折标系数 kgce/m³（留空=1.2143） | D27: 有燃气公司热值时按实测折算
B28: 计算结果（自动） | C28: 结果 | D28: 说明
B29: 可计入的绿电交易与绿证电量 kWh | C29: =IF(AND(C5>0,C8+C9*1000>C5),C5,C8+C9*1000) -> 0 | D29: 超过外购电量的部分不计
B30: 综合能耗 tce | C30: =IF(SUM(F5:F7,F10:F19)>0,SUM(F5:F7,F10:F19)-C21-C22,"") -> 3187.0103
B31: 可再生能源消费量 tce | C31: =(C6+C7+C29)*参数!$E$4/1000+C19 -> 319.54
B32: 可再生能源利用率 % | C32: =IF(C30="","",IF(C30=0,"",C31/C30*100)) -> 10.026325 | D32: 指标3
B33: 使用的电网排放因子 kgCO2/kWh | C33: =IF(C26<>"",C26,IF(C25="市场法",参数!$B$36,IFERROR(VLOOKUP(SUBSTITUTE(SUBSTITUTE(SUBSTITUTE(SUBSTITUTE(SUBSTITUTE(SUBSTITUTE(1基本信息!$C$7,"省",""),"市",""),"自治区",""),"壮族",""),"回族",""),"维吾尔",""),参数!$A$4:$B$33,2,FALSE()),参数!$B$35))) -> 0.5827 | D33: 2023年因子
B34: 二氧化碳排放 tCO2 | C34: =IF(C30="","",H5+SUM(H10:H17)+C20) -> 12010.152 | D34: 指标2的分子

Sheet 3资源产出
B2: 3 资源与产出（评价年；投资和产值取近三年）
B3: 产值用统计报表的工业总产值（现价），不要用营业收入
B4: 项目 | C4: 数量 | D4: 单位 | E4: 说明
B5: 工业总产值（评价年，现价） | C5: 62000 | D5: 万元 | E5: 强度指标和土地产出率的分母
B6: 合格产品产量 | C6: 48000 | D6: 产品单位 | E6: 按产量口径时使用
B7: 近三年工业总产值合计 | C7: 171000 | D7: 万元 | E7: 指标10的分母
B8: 近三年绿色低碳改造项目投资额 | C8: 4000 | D8: 万元 | E8: 只计真实实施、有立项和验收材料的项目
B10: 取水量（生产、辅助、附属系统） | C10: 96000 | D10: m³ | E10: 不含基建改造、消防、外供
B11: 重复利用水量（循环水+回用水） | C11: 1104000 | D11: m³ | E11: 指标7
B13: 主要原材料名称 | C13: 钢材（棒料、锻件毛坯）
B14: 主要原材料消耗量 | C14: 21800 | E14: 单位见下一行
B15: 原材料计量单位 | C15: t
B17: 一般工业固体废物产生量 | C17: 2350 | D17: t | E17: 不含危险废物
B18: 一般工业固废综合利用量（不含外购） | C18: 2256 | D18: t
B19: 综合利用往年贮存量 | C19: 0 | D19: t | E19: 计入分母
B21: 主要污染物名称 | C21: VOCs | E21: 选行业最有代表性的一项，如COD、VOCs、颗粒物
B22: 主要污染物产生或排放量 | C22: 6.2 | E22: 与对标值口径一致（产生量或排放量）
B23: 污染物计量单位 | C23: t
B25: 工厂用地面积（不动产权证） | C25: 66700 | D25: m² | E25: 1亩≈666.67 m²
B26: 总产能（按产能算土地产出率时填） | D26: 产品单位

Sheet 4定性与系统
B2: 4 定性项与能碳管理系统
B3: 能碳系统必须建成运行才计分；功能以能拿出运行截图和数据导出为准
B4: 项目 | C4: 是/否 | D4: 说明 | E4: 计分功能数
B5: 能碳管理系统是否已建成运行 | C5: 是 | D5: 引领值8项，每项0.75分；没说明是否建成运行时按待定处理 | E5: =IF(C5="是",MIN(COUNTIF(C7:C18,"是"),12),IF(C5="否",0,"")) -> 6
B7: 功能1：能耗查询 | C7: 是
B8: 功能2：能源消费量和强度计算 | C8: 是
B9: 功能3：能源消费分析与用能策略推荐 | C9: 是
B10: 功能4：能效对标 | C10: 是
B11: 功能5：能流分析 | C11: 是
B12: 功能6：能效平衡与优化 | C12: 否
B13: 功能7：用能与碳排放预算管理 | C13: 否
B14: 功能8：碳排放 | C14: 是
B15: 功能9：碳足迹核算 | C15: 否
B16: 功能10：供应链碳管理 | C16: 否
B17: 功能11：碳核查支撑 | C17: 否
B18: 功能12：碳资产管理 | C18: 否
B19: 定性指标 | C19: A/B/C | D19: A档 | E19: B档 | F19: C档
B20: 指标9 生产工艺和设备先进性（6分） | C20: A | D20: 主要工序的工艺设备能逐项对上国家推荐目录或行业规范条件，有合同/铭牌/验收证明，且无淘汰类设备 | E20: 部分能对上，或证明材料不全 | F20: 拿不出对应证明（若还有淘汰类设备，先解决合规问题）
B21: 指标12 绿色设计（8分） | C21: C | D21: 已按 GB/T 24256 形成产品绿色设计及验证报告，并有环境绩效改善的证据 | E21: 有设计改进记录，但没有成体系的报告或验证 | F21: 未开展
B22: 指标13 产品碳足迹（8分） | C22: B | D22: 主要产品已按 GB/T 24067 等完成碳足迹量化并出具报告 | E22: 只做了部分主要产品，或方法不符合 GB/T 24067 | F22: 未开展
B23: 三档按满分、半分、零分估计，是本工具的经验估计，平台细则以填报说明为准

Sheet 5对标值
B2: 5 对标值（决定得分，必须有来源）
B3: 引领值≈行业前5%先进水平，基准值≈行业平均。没有可靠来源就留空，宁可待定也不要估
B4: 指标 | C4: 引领值 | D4: 基准值 | E4: 来源（文件名、条款、年份） | F4: 口径
B5: 指标1 能源消耗强度 | C5: 0.045 | D5: 0.07 | E5: 演示值，非真实行业数据 | F5: tce/万元或tce/产品；有能耗限额标准用1级/2级
B6: 指标2 碳排放强度 | C6: 0.16 | D6: 0.3 | E6: 演示值，非真实行业数据 | F6: tCO2/万元或tCO2/产品
B7: 指标3 可再生能源利用率 | C7: 12 | D7: 2 | E7: 演示值，非真实行业数据 | F7: %
B8: 指标5 原材料消耗强度 | F8: 原材料单位/万元或/产品
B9: 指标6 取水强度 | C9: 1.2 | D9: 3 | E9: 演示值，非真实行业数据 | F9: m³/万元或m³/产品；有用水定额用先进值/通用值
B10: 指标7 工业用水重复利用率 | C10: 90 | D10: 70 | E10: 演示值，非真实行业数据 | F10: %
B11: 指标8 一般工业固废综合利用率 | C11: 95 | D11: 80 | E11: 演示值，非真实行业数据 | F11: %
B12: 指标10 绿色低碳改造投资额占比 | C12: 2.5 | D12: 0.5 | E12: 演示值，非真实行业数据 | F12: %（近三年投资÷三年总产值）
B13: 指标11 主要污染物产生或排放强度 | F13: 污染物单位/万元或/产品
B14: 指标14 土地产出率 | C14: 1 | D14: 0.5 | E14: 演示值，非真实行业数据 | F14: 万元/m²（或产品单位/m²）
B16: 指标4能碳管理系统为固定值（引领8项、基准0项）；指标9、12、13为定性项，不需要对标值

Sheet 6得分
B2: 6 得分（自动计算，请勿修改）
B3: 按 GB/T 36132—2025 和工信部年度评价要求的14项指标；定量项在基准值和引领值之间线性得分 | F3: 一级指标 | G3: 满分 | H3: 确定得分 | I3: 上限 | P3: 强度分母
B4: 确定分 | C4: =SUM(J13:J26) -> 63.948106 | F4: 能源低碳化 | G4: =SUMIF($B$13:$B$26,F4,$E$13:$E$26) -> 30 | H4: =SUMIF($B$13:$B$26,F4,$J$13:$J$26) -> 22.945567 | I4: =H4+SUMPRODUCT(($B$13:$B$26=F4)*($J$13:$J$26="")*$E$13:$E$26) -> 22.945567 | P4: =IF(1基本信息!$C$17="产量",3资源产出!$C$6,3资源产出!$C$5) -> 62000
B5: 待定分（缺数据或缺对标值的满分合计） | C5: =SUMPRODUCT((J13:J26="")*E13:E26) -> 14 | F5: 资源高效化 | G5: =SUMIF($B$13:$B$26,F5,$E$13:$E$26) -> 30 | H5: =SUMIF($B$13:$B$26,F5,$J$13:$J$26) -> 20.451613 | I5: =H5+SUMPRODUCT(($B$13:$B$26=F5)*($J$13:$J$26="")*$E$13:$E$26) -> 28.451613 | O5: 否决标志 | P5: =OR(COUNTIF(1基本信息!$C$21:$C$28,"是")>0,1基本信息!$C$32="否",COUNTIF(1基本信息!$C$33:$C$36,"未建立")>0) -> FALSE
B6: 上限 | C6: =C4+C5 -> 77.948106 | F6: 生产洁净化 | G6: =SUMIF($B$13:$B$26,F6,$E$13:$E$26) -> 16 | H6: =SUMIF($B$13:$B$26,F6,$J$13:$J$26) -> 9.6783626 | I6: =H6+SUMPRODUCT(($B$13:$B$26=F6)*($J$13:$J$26="")*$E$13:$E$26) -> 15.678363 | O6: 待核实标志 | P6: =OR(COUNTIF(1基本信息!$C$21:$C$29,"不确定")>0,COUNTBLANK(1基本信息!$C$21:$C$29)>0,AND(1基本信息!$C$32<>"是",1基本信息!$C$32<>"否"),COUNTBLANK(1基本信息!$C$33:$C$36)>0) -> FALSE
B7: 门槛核查 | C7: =IF($P$5,"存在否决项",IF($P$7,"门槛存疑（近三年有违法违规记录）",IF($P$6,"有待核实项","通过"))) -> 通过 | F7: 产品绿色化 | G7: =SUMIF($B$13:$B$26,F7,$E$13:$E$26) -> 16 | H7: =SUMIF($B$13:$B$26,F7,$J$13:$J$26) -> 4 | I7: =H7+SUMPRODUCT(($B$13:$B$26=F7)*($J$13:$J$26="")*$E$13:$E$26) -> 4 | O7: 存疑标志 | P7: =1基本信息!$C$29="是" -> FALSE
B8: 适用分数线（目标层级） | C8: =IF($P$10="国家级",IF(1基本信息!$C$41="","",1基本信息!$C$41),IF($P$10="市级",IF(1基本信息!$C$39<>"",1基本信息!$C$39,IF(1基本信息!$C$11="是",参数!$B$40,参数!$B$41)),IF(1基本信息!$C$40<>"",1基本信息!$C$40,IF(1基本信息!$C$11="是",参数!$B$40,参数!$B$41)))) -> 75 | F8: 用地集约化 | G8: =SUMIF($B$13:$B$26,F8,$E$13:$E$26) -> 8 | H8: =SUMIF($B$13:$B$26,F8,$J$13:$J$26) -> 6.8725637 | I8: =H8+SUMPRODUCT(($B$13:$B$26=F8)*($J$13:$J$26="")*$E$13:$E$26) -> 6.8725637 | O8: 按分数结论 | P8: =IF(C8="","需对比本地区平均水平",IF(C4>=C8-0.000001,"确定分已过线",IF(C5>30,"信息不足",IF(C6>=C8-0.000001,"有希望，待补齐","目前达不到")))) -> 有希望，待补齐
B9: 结论 | C9: =IF(AND($P$10="国家级",$P$9="国家级"),"已是国家级，看动态管理",IF($P$5,"不具备申报条件",IF(AND($P$10="国家级",OR(1基本信息!$C$10="否",AND($P$9<>"省级",$P$9<>"国家级"))),"当年不能报（须先列入本地区省级名单，且属C类制造业）",IF($P$7,"门槛存疑，先向当地确认；按分数："&$P$8,$P$8)))) -> 有希望，待补齐 | O9: 当前层级（直辖市市级=省级） | P9: =IF(AND(1基本信息!$C$13="市级",OR(1基本信息!$C$7="北京",1基本信息!$C$7="上海",1基本信息!$C$7="天津",1基本信息!$C$7="重庆")),"省级",IF(1基本信息!$C$13="","无",1基本信息!$C$13)) -> 市级
B10: 离分数线还差 | C10: =IF(C8="","",MAX(0,C8-C4)) -> 11.051894 | O10: 目标层级（直辖市市级=省级） | P10: =IF(AND(1基本信息!$C$12="市级",OR(1基本信息!$C$7="北京",1基本信息!$C$7="上海",1基本信息!$C$7="天津",1基本信息!$C$7="重庆")),"省级",IF(1基本信息!$C$12="","省级",1基本信息!$C$12)) -> 省级
B11: 分数线说明 | C11: =IF($P$10="国家级","国家级没有固定分数线，填本地区已有国家绿色工厂平均分作比较",IF(OR(AND($P$10="市级",1基本信息!$C$39=""),AND($P$10<>"市级",1基本信息!$C$40="")),"缺省值（参照安徽2026年口径），以当地通知为准","来自当地通知（用户填写）")) -> 缺省值（参照安徽2026年口径），以当地通知为准
A12: 序号 | B12: 一级指标 | C12: 指标 | D12: 类型 | E12: 满分 | F12: 实际值 | G12: 单位 | H12: 引领值 | I12: 基准值 | J12: 得分 | K12: 状态
A13: 1 | B13: 能源低碳化 | C13: 能源消耗强度 | D13: 逆向 | E13: 8 | F13: =IF(OR(2能源与碳!$C$30="",N($P$4)=0),"",2能源与碳!$C$30/$P$4) -> 0.051403392 | G13: =IF(1基本信息!$C$17="产量","tce/"&1基本信息!$C$18,"tce/万元") -> tce/万元 | H13: =IF(5对标值!$C$5="","",5对标值!$C$5) -> 0.045 | I13: =IF(5对标值!$D$5="","",5对标值!$D$5) -> 0.07 | J13: =IF(OR(F13="",H13="",I13=""),"",E13*IF(H13=I13,IF(IF(D13="逆向",F13<=H13,F13>=H13),1,0),MAX(0,MIN(1,IF(D13="逆向",(MAX(H13,I13)-F13)/(MAX(H13,I13)-MIN(H13,I13)),(F13-MIN(H13,I13))/(MAX(H13,I13)-MIN(H13,I13))))))) -> 5.9509146 | K13: =IF(J13="",IF(F13="","缺数据","缺对标值"),IF(J13>=E13*0.9999,"满分",IF(J13<=E13*0.0001,"零分","部分得分"))) -> 部分得分
A14: 2 | B14: 能源低碳化 | C14: 碳排放强度 | D14: 逆向 | E14: 8 | F14: =IF(OR(2能源与碳!$C$34="",N($P$4)=0),"",2能源与碳!$C$34/$P$4) -> 0.19371214 | G14: =IF(1基本信息!$C$17="产量","tCO2/"&1基本信息!$C$18,"tCO2/万元") -> tCO2/万元 | H14: =IF(5对标值!$C$6="","",5对标值!$C$6) -> 0.16 | I14: =IF(5对标值!$D$6="","",5对标值!$D$6) -> 0.3 | J14: =IF(OR(F14="",H14="",I14=""),"",E14*IF(H14=I14,IF(IF(D14="逆向",F14<=H14,F14>=H14),1,0),MAX(0,MIN(1,IF(D14="逆向",(MAX(H14,I14)-F14)/(MAX(H14,I14)-MIN(H14,I14)),(F14-MIN(H14,I14))/(MAX(H14,I14)-MIN(H14,I14))))))) -> 6.0735923 | K14: =IF(J14="",IF(F14="","缺数据","缺对标值"),IF(J14>=E14*0.9999,"满分",IF(J14<=E14*0.0001,"零分","部分得分"))) -> 部分得分
A15: 3 | B15: 能源低碳化 | C15: 可再生能源利用率 | D15: 正向 | E15: 8 | F15: =2能源与碳!$C$32 -> 10.026325 | G15: % | H15: =IF(5对标值!$C$7="","",IF(LEFT(CELL("format",5对标值!$C$7),1)="P",5对标值!$C$7*100,5对标值!$C$7)) -> 12 | I15: =IF(5对标值!$D$7="","",IF(LEFT(CELL("format",5对标值!$D$7),1)="P",5对标值!$D$7*100,5对标值!$D$7)) -> 2 | J15: =IF(OR(F15="",H15="",I15=""),"",E15*IF(H15=I15,IF(IF(D15="逆向",F15<=H15,F15>=H15),1,0),MAX(0,MIN(1,IF(D15="逆向",(MAX(H15,I15)-F15)/(MAX(H15,I15)-MIN(H15,I15)),(F15-MIN(H15,I15))/(MAX(H15,I15)-MIN(H15,I15))))))) -> 6.4210597 | K15: =IF(J15="",IF(F15="","缺数据","缺对标值"),IF(J15>=E15*0.9999,"满分",IF(J15<=E15*0.0001,"零分","部分得分"))) -> 部分得分
A16: 4 | B16: 能源低碳化 | C16: 能碳管理系统平台功能符合数量 | D16: 正向 | E16: 6 | F16: =4定性与系统!$E$5 -> 6 | G16: 项 | H16: 8 | I16: 0 | J16: =IF(OR(F16="",H16="",I16=""),"",E16*IF(H16=I16,IF(IF(D16="逆向",F16<=H16,F16>=H16),1,0),MAX(0,MIN(1,IF(D16="逆向",(MAX(H16,I16)-F16)/(MAX(H16,I16)-MIN(H16,I16)),(F16-MIN(H16,I16))/(MAX(H16,I16)-MIN(H16,I16))))))) -> 4.5 | K16: =IF(J16="",IF(F16="","缺数据","缺对标值"),IF(J16>=E16*0.9999,"满分",IF(J16<=E16*0.0001,"零分","部分得分"))) -> 部分得分
A17: 5 | B17: 资源高效化 | C17: 原材料消耗强度 | D17: 逆向 | E17: 8 | F17: =IF(OR(3资源产出!$C$14="",N($P$4)=0),"",3资源产出!$C$14/$P$4) -> 0.3516129 | G17: =IF(1基本信息!$C$17="产量",3资源产出!$C$15&"/"&1基本信息!$C$18,3资源产出!$C$15&"/万元") -> t/万元 | H17: =IF(5对标值!$C$8="","",5对标值!$C$8) | I17: =IF(5对标值!$D$8="","",5对标值!$D$8) | J17: =IF(OR(F17="",H17="",I17=""),"",E17*IF(H17=I17,IF(IF(D17="逆向",F17<=H17,F17>=H17),1,0),MAX(0,MIN(1,IF(D17="逆向",(MAX(H17,I17)-F17)/(MAX(H17,I17)-MIN(H17,I17)),(F17-MIN(H17,I17))/(MAX(H17,I17)-MIN(H17,I17))))))) | K17: =IF(J17="",IF(F17="","缺数据","缺对标值"),IF(J17>=E17*0.9999,"满分",IF(J17<=E17*0.0001,"零分","部分得分"))) -> 缺对标值
A18: 6 | B18: 资源高效化 | C18: 取水强度 | D18: 逆向 | E18: 8 | F18: =IF(OR(3资源产出!$C$10="",N($P$4)=0),"",3资源产出!$C$10/$P$4) -> 1.5483871 | G18: =IF(1基本信息!$C$17="产量","m³/"&1基本信息!$C$18,"m³/万元") -> m³/万元 | H18: =IF(5对标值!$C$9="","",5对标值!$C$9) -> 1.2 | I18: =IF(5对标值!$D$9="","",5对标值!$D$9) -> 3 | J18: =IF(OR(F18="",H18="",I18=""),"",E18*IF(H18=I18,IF(IF(D18="逆向",F18<=H18,F18>=H18),1,0),MAX(0,MIN(1,IF(D18="逆向",(MAX(H18,I18)-F18)/(MAX(H18,I18)-MIN(H18,I18)),(F18-MIN(H18,I18))/(MAX(H18,I18)-MIN(H18,I18))))))) -> 6.4516129 | K18: =IF(J18="",IF(F18="","缺数据","缺对标值"),IF(J18>=E18*0.9999,"满分",IF(J18<=E18*0.0001,"零分","部分得分"))) -> 部分得分
A19: 7 | B19: 资源高效化 | C19: 工业用水重复利用率 | D19: 正向 | E19: 8 | F19: =IF(OR(3资源产出!$C$10="",3资源产出!$C$11=""),"",IF(3资源产出!$C$10+3资源产出!$C$11>0,3资源产出!$C$11/(3资源产出!$C$10+3资源产出!$C$11)*100,"")) -> 92 | G19: % | H19: =IF(5对标值!$C$10="","",IF(LEFT(CELL("format",5对标值!$C$10),1)="P",5对标值!$C$10*100,5对标值!$C$10)) -> 90 | I19: =IF(5对标值!$D$10="","",IF(LEFT(CELL("format",5对标值!$D$10),1)="P",5对标值!$D$10*100,5对标值!$D$10)) -> 70 | J19: =IF(OR(F19="",H19="",I19=""),"",E19*IF(H19=I19,IF(IF(D19="逆向",F19<=H19,F19>=H19),1,0),MAX(0,MIN(1,IF(D19="逆向",(MAX(H19,I19)-F19)/(MAX(H19,I19)-MIN(H19,I19)),(F19-MIN(H19,I19))/(MAX(H19,I19)-MIN(H19,I19))))))) -> 8 | K19: =IF(J19="",IF(F19="","缺数据","缺对标值"),IF(J19>=E19*0.9999,"满分",IF(J19<=E19*0.0001,"零分","部分得分"))) -> 满分
A20: 8 | B20: 资源高效化 | C20: 一般工业固体废物综合利用率 | D20: 正向 | E20: 6 | F20: =IF(OR(3资源产出!$C$17="",3资源产出!$C$18=""),"",IF(3资源产出!$C$17+N(3资源产出!$C$19)>0,3资源产出!$C$18/(3资源产出!$C$17+N(3资源产出!$C$19))*100,"")) -> 96 | G20: % | H20: =IF(5对标值!$C$11="","",IF(LEFT(CELL("format",5对标值!$C$11),1)="P",5对标值!$C$11*100,5对标值!$C$11)) -> 95 | I20: =IF(5对标值!$D$11="","",IF(LEFT(CELL("format",5对标值!$D$11),1)="P",5对标值!$D$11*100,5对标值!$D$11)) -> 80 | J20: =IF(OR(F20="",H20="",I20=""),"",E20*IF(H20=I20,IF(IF(D20="逆向",F20<=H20,F20>=H20),1,0),MAX(0,MIN(1,IF(D20="逆向",(MAX(H20,I20)-F20)/(MAX(H20,I20)-MIN(H20,I20)),(F20-MIN(H20,I20))/(MAX(H20,I20)-MIN(H20,I20))))))) -> 6 | K20: =IF(J20="",IF(F20="","缺数据","缺对标值"),IF(J20>=E20*0.9999,"满分",IF(J20<=E20*0.0001,"零分","部分得分"))) -> 满分
A21: 9 | B21: 生产洁净化 | C21: 生产工艺和设备先进性 | D21: 定性 | E21: 6 | F21: =LEFT(UPPER(TRIM(4定性与系统!$C$20)),1) -> A | G21: 档 | H21: — | I21: — | J21: =IF(F21="A",E21,IF(F21="B",E21*0.5,IF(F21="C",0,""))) -> 6 | K21: =IF(J21="","未说明",IF(F21="A","满分",IF(F21="B","部分得分","零分"))) -> 满分
A22: 10 | B22: 生产洁净化 | C22: 绿色低碳改造升级项目投资额占比 | D22: 正向 | E22: 4 | F22: =IF(OR(3资源产出!$C$8="",N(3资源产出!$C$7)=0),"",3资源产出!$C$8/3资源产出!$C$7*100) -> 2.3391813 | G22: % | H22: =IF(5对标值!$C$12="","",IF(LEFT(CELL("format",5对标值!$C$12),1)="P",5对标值!$C$12*100,5对标值!$C$12)) -> 2.5 | I22: =IF(5对标值!$D$12="","",IF(LEFT(CELL("format",5对标值!$D$12),1)="P",5对标值!$D$12*100,5对标值!$D$12)) -> 0.5 | J22: =IF(OR(F22="",H22="",I22=""),"",E22*IF(H22=I22,IF(IF(D22="逆向",F22<=H22,F22>=H22),1,0),MAX(0,MIN(1,IF(D22="逆向",(MAX(H22,I22)-F22)/(MAX(H22,I22)-MIN(H22,I22)),(F22-MIN(H22,I22))/(MAX(H22,I22)-MIN(H22,I22))))))) -> 3.6783626 | K22: =IF(J22="",IF(F22="","缺数据","缺对标值"),IF(J22>=E22*0.9999,"满分",IF(J22<=E22*0.0001,"零分","部分得分"))) -> 部分得分
A23: 11 | B23: 生产洁净化 | C23: 主要污染物产生或排放强度 | D23: 逆向 | E23: 6 | F23: =IF(OR(3资源产出!$C$22="",N($P$4)=0),"",3资源产出!$C$22/$P$4) -> 0.0001 | G23: =IF(1基本信息!$C$17="产量",3资源产出!$C$23&"/"&1基本信息!$C$18,3资源产出!$C$23&"/万元") -> t/万元 | H23: =IF(5对标值!$C$13="","",5对标值!$C$13) | I23: =IF(5对标值!$D$13="","",5对标值!$D$13) | J23: =IF(OR(F23="",H23="",I23=""),"",E23*IF(H23=I23,IF(IF(D23="逆向",F23<=H23,F23>=H23),1,0),MAX(0,MIN(1,IF(D23="逆向",(MAX(H23,I23)-F23)/(MAX(H23,I23)-MIN(H23,I23)),(F23-MIN(H23,I23))/(MAX(H23,I23)-MIN(H23,I23))))))) | K23: =IF(J23="",IF(F23="","缺数据","缺对标值"),IF(J23>=E23*0.9999,"满分",IF(J23<=E23*0.0001,"零分","部分得分"))) -> 缺对标值
A24: 12 | B24: 产品绿色化 | C24: 绿色设计 | D24: 定性 | E24: 8 | F24: =LEFT(UPPER(TRIM(4定性与系统!$C$21)),1) -> C | G24: 档 | H24: — | I24: — | J24: =IF(F24="A",E24,IF(F24="B",E24*0.5,IF(F24="C",0,""))) -> 0 | K24: =IF(J24="","未说明",IF(F24="A","满分",IF(F24="B","部分得分","零分"))) -> 零分
A25: 13 | B25: 产品绿色化 | C25: 产品碳足迹 | D25: 定性 | E25: 8 | F25: =LEFT(UPPER(TRIM(4定性与系统!$C$22)),1) -> B | G25: 档 | H25: — | I25: — | J25: =IF(F25="A",E25,IF(F25="B",E25*0.5,IF(F25="C",0,""))) -> 4 | K25: =IF(J25="","未说明",IF(F25="A","满分",IF(F25="B","部分得分","零分"))) -> 部分得分
A26: 14 | B26: 用地集约化 | C26: 土地产出率 | D26: 正向 | E26: 8 | F26: =IF(OR(3资源产出!$C$5="",N(3资源产出!$C$25)=0),"",3资源产出!$C$5/3资源产出!$C$25) -> 0.92953523 | G26: 万元/m² | H26: =IF(5对标值!$C$14="","",5对标值!$C$14) -> 1 | I26: =IF(5对标值!$D$14="","",5对标值!$D$14) -> 0.5 | J26: =IF(OR(F26="",H26="",I26=""),"",E26*IF(H26=I26,IF(IF(D26="逆向",F26<=H26,F26>=H26),1,0),MAX(0,MIN(1,IF(D26="逆向",(MAX(H26,I26)-F26)/(MAX(H26,I26)-MIN(H26,I26)),(F26-MIN(H26,I26))/(MAX(H26,I26)-MIN(H26,I26))))))) -> 6.8725637 | K26: =IF(J26="",IF(F26="","缺数据","缺对标值"),IF(J26>=E26*0.9999,"满分",IF(J26<=E26*0.0001,"零分","部分得分"))) -> 部分得分
B28: 定性项（9、12、13）按满分、半分、零分估计；重点行业以平台的行业评价要求为准。结果是按规则推算，不是官方评审结论。

Sheet 参数
B2: 参数（引用的缺省值与出处，一般不需要改）
A3: 省份 | B3: 2023年电力排放因子 kgCO2/kWh | D3: 能源 | E3: 折标系数 | F3: 单位 | H3: 燃料 | I3: 低位热值 | J3: 含碳量 tC/TJ | K3: 碳氧化率 | L3: 热值单位折算 | M3: 排放因子 tCO2/单位
A4: 北京 | B4: 0.5554 | D4: 电力（当量值） | E4: 0.1229 | F4: kgce/kWh | H4: 天然气（每m³） | I4: 389.31 | J4: 15.32 | K4: 0.99 | L4: 10000 | M4: =I4/L4/1000*J4*K4*44/12 -> 0.0021650152
A5: 天津 | B5: 0.6796 | D5: 天然气 | E5: 1.2143 | F5: kgce/m³ | H5: 柴油（每t） | I5: 42.652 | J5: 20.2 | K5: 0.98 | L5: 1 | M5: =I5/L5/1000*J5*K5*44/12 -> 3.0959096
A6: 河北 | B6: 0.6516 | D6: 柴油 | E6: 1.4571 | F6: kgce/kg | H6: 汽油（每t） | I6: 43.07 | J6: 18.9 | K6: 0.98 | L6: 1 | M6: =I6/L6/1000*J6*K6*44/12 -> 2.925056
A7: 山西 | B7: 0.6634 | D7: 汽油 | E7: 1.4714 | F7: kgce/kg | H7: 液化石油气（每t） | I7: 50.179 | J7: 17.2 | K7: 0.98 | L7: 1 | M7: =I7/L7/1000*J7*K7*44/12 -> 3.1013298
A8: 内蒙古 | B8: 0.6479 | D8: 液化石油气 | E8: 1.7143 | F8: kgce/kg | H8: 燃料油（每t） | I8: 41.816 | J8: 21.1 | K8: 0.98 | L8: 1 | M8: =I8/L8/1000*J8*K8*44/12 -> 3.1704612
A9: 辽宁 | B9: 0.4878 | D9: 燃料油 | E9: 1.4286 | F9: kgce/kg | H9: 原煤（每t） | I9: 20.908 | J9: 26.37 | K9: 0.94 | L9: 1 | M9: =I9/L9/1000*J9*K9*44/12 -> 1.9002988
A10: 吉林 | B10: 0.4671 | D10: 原煤 | E10: 0.7143 | F10: kgce/kg | H10: 焦炭（每t） | I10: 28.435 | J10: 29.5 | K10: 0.93 | L10: 1 | M10: =I10/L10/1000*J10*K10*44/12 -> 2.8604188
A11: 黑龙江 | B11: 0.5229 | D11: 焦炭 | E11: 0.9714 | F11: kgce/kg | H11: 外购热力（每GJ） | M11: 0.11
A12: 上海 | B12: 0.5737 | D12: 热力 | E12: 34.12 | F12: kgce/GJ | H12: 出处：GB/T 32150 常用缺省值；天然气低位热值单位为 GJ/万m³，故折算除以10000
A13: 江苏 | B13: 0.5827
A14: 浙江 | B14: 0.4974 | D14: 出处：GB/T 2589—2020 附录A参考系数；电力按国家统计局能源统计口径取当量值
A15: 安徽 | B15: 0.6553
A16: 福建 | B16: 0.4211
A17: 江西 | B17: 0.5836
A18: 山东 | B18: 0.6191
A19: 河南 | B19: 0.5897
A20: 湖北 | B20: 0.4044
A21: 湖南 | B21: 0.4976
A22: 广东 | B22: 0.4419
A23: 广西 | B23: 0.4476
A24: 海南 | B24: 0.3648
A25: 重庆 | B25: 0.5581
A26: 四川 | B26: 0.1564
... A36: 全国（不含市场化交易非化石电量，市场法用） | B36: 0.6096
A37: 出处：生态环境部 国家统计局 公告2025年第47号（2023年电力二氧化碳排放因子）
A39: 缺省分数线（当地通知未给或未填时使用）
A40: 重点行业 | B40: 60
A41: 非重点行业 | B41: 75
A42: 出处：安徽省工信厅2026年度省级绿色工厂推荐通知（原则上重点≥60、非重点≥75）；其他地区以当地通知为准
